magic_words/__init__.py
magic_words/backoff_hack_qa.py
magic_words/batch_compute_score.py
magic_words/compute_score.py
magic_words/easy_gcg.py
magic_words/forward_gcg.py
magic_words/forward_reach.py
magic_words/get_answer.py
magic_words/prompt_hack.py
magic_words/prompt_hack_qa.py
magic_words/search_limiters.py
magic_words/utils.py
magic_words-0.1.1.dist-info/LICENSE
magic_words-0.1.1.dist-info/METADATA
magic_words-0.1.1.dist-info/WHEEL
magic_words-0.1.1.dist-info/top_level.txt
magic_words-0.1.1.dist-info/RECORD
