Metadata-Version: 2.1
Name: magic-words
Version: 0.1.1
Summary: Measuring the controllability of LLMs -- from arxiv.org/abs/2310.04444
License: MIT
License-File: LICENSE
